flowtees.py
helpers/__init__.py
helpers/build_files.py
helpers/utilities.py
flowtees-0.1.9.dist-info/LICENSE
flowtees-0.1.9.dist-info/METADATA
flowtees-0.1.9.dist-info/WHEEL
flowtees-0.1.9.dist-info/entry_points.txt
flowtees-0.1.9.dist-info/top_level.txt
flowtees-0.1.9.dist-info/RECORD
