Metadata-Version: 2.1
Name: flowtees
Version: 0.1.9
Summary: This tool provides support in the conversion process of converting AtlasKit Flow components to TypeScript. It takes the trivial work out of the conversion.
Home-page: https://bitbucket.org/patrickcylai/flowtees/src/master/
Author: Patrick Lai
Author-email: plai@atlassian.com
License: UNKNOWN
Platform: UNKNOWN
Classifier: Programming Language :: Python :: 3
Classifier: License :: OSI Approved :: Apache Software License
Classifier: Operating System :: OS Independent
Classifier: Development Status :: 3 - Alpha
Classifier: Environment :: Console
Classifier: Intended Audience :: Developers
Classifier: Natural Language :: English
Classifier: Topic :: Software Development
Requires-Python: >=3.5
Requires-Dist: Click
Requires-Dist: colorama
